tsst/__init__.py
tsst/base.py
tsst/cli.py
tsst/constant.py
tsst/error.py
tsst/event.py
tsst/main.py
tsst/system_code.py
tsst/utils.py
tsst/validate.py
tsst/account/__init__.py
tsst/account/base.py
tsst/account/base_validate.py
tsst/account/sino/__init__.py
tsst/account/sino/main.py
tsst/account/sino/validate.py
tsst/backtest/__init__.py
tsst/backtest/base_validate.py
tsst/backtest/new_base.py
tsst/broker/__init__.py
tsst/broker/capital.py
tsst/broker/sino.py
tsst/login/__init__.py
tsst/login/base.py
tsst/login/base_validate.py
tsst/login/capital/__init__.py
tsst/login/capital/main.py
tsst/login/capital/validate.py
tsst/login/sino/__init__.py
tsst/login/sino/main.py
tsst/login/sino/validate.py
tsst/static/__init__.py
tsst/static/holidays_search_from_2017.csv
tsst/trade/__init__.py
tsst/trade/order/__init__.py
tsst/trade/order/base.py
tsst/trade/order/base_validate.py
tsst/trade/order/capital/__init__.py
tsst/trade/order/capital/main.py
tsst/trade/order/capital/validate.py
tsst/trade/order/sino/__init__.py
tsst/trade/order/sino/main.py
tsst/trade/order/sino/validate.py
tsst/trade/quote/__init__.py
tsst/trade/quote/base.py
tsst/trade/quote/base_validate.py
tsst/trade/quote/capital/__init__.py
tsst/trade/quote/capital/main.py
tsst/trade/quote/capital/validate.py
tsst/trade/quote/sino/__init__.py
tsst/trade/quote/sino/main.py
tsst/trade/quote/sino/validate.py
tsst-0.8.7.dist-info/METADATA
tsst-0.8.7.dist-info/WHEEL
tsst-0.8.7.dist-info/entry_points.txt
tsst-0.8.7.dist-info/top_level.txt
tsst-0.8.7.dist-info/RECORD
