Metadata-Version: 2.4
Name: tsst
Version: 0.8.7
Summary: TSST is an integration platform for Taiwan brokerage Python APIs, enabling quick switching between different brokerage APIs using a unified trading logic.
Requires-Python: >=3.9
Requires-Dist: blinker>=1.9.0
Requires-Dist: click>=8.1.7
Requires-Dist: comtypes>=1.4.8
Requires-Dist: pandas>=2.2.3
Requires-Dist: polars-talib>=0.1.4
Requires-Dist: polars>=1.15.0
Requires-Dist: pyarrow>=20.0.0
Requires-Dist: pydantic>=2.9.2
Requires-Dist: pytest>=8.3.4
Requires-Dist: python-dotenv>=1.0.1
Requires-Dist: pywin32>=308; sys_platform == "win32"
Requires-Dist: rich>=13.9.4
Requires-Dist: setuptools>=75.6.0
Requires-Dist: shioaji>=1.2.5
Requires-Dist: tabulate>=0.9.0
Requires-Dist: tsst-sino-backtest-v2>=0.2.0
Requires-Dist: tornado>=6.1
